django_simple_files
