Metadata-Version: 1.0
Name: django-simple-files
Version: 0.0.9
Summary: django-simple-files
Home-page: https://github.com/lvjiyong/django-simple-files
Author: lvjiyong
Author-email: lvjiyong@gmail.com
License: Apache2.0
Platform: any
